security_scripts/__init__.py
security_scripts/kli.py
security_scripts/cfg/__init__.py
security_scripts/cfg/defaults.cfg
security_scripts/controls/__init__.py
security_scripts/controls/audit.py
security_scripts/controls/buttons.py
security_scripts/controls/defaults.cfg
security_scripts/controls/tests.py
security_scripts/information/L1_preport.py
security_scripts/information/__init__.py
security_scripts/information/attachment_priority.csv
security_scripts/information/betterparse.py
security_scripts/information/defaults.cfg
security_scripts/information/find_by_content.py
security_scripts/information/find_flow.py
security_scripts/information/ll.py
security_scripts/information/preport.py
security_scripts/information/report.py
security_scripts/information/vault.py
security_scripts/information/vault_flow.py
security_scripts/information/xreport.py
security_scripts/information/lib/L0A.py
security_scripts/information/lib/L0A_L0B.py
security_scripts/information/lib/L0B_L1.py
security_scripts/information/lib/L1_L2.py
security_scripts/information/lib/L2_L3.py
security_scripts/information/lib/Liam.py
security_scripts/information/lib/__init__.py
security_scripts/information/lib/assets.py
security_scripts/information/lib/aws_utils.py
security_scripts/information/lib/certificates.py
security_scripts/information/lib/commands.py
security_scripts/information/lib/instances.py
security_scripts/information/lib/links.py
security_scripts/information/lib/load_balancer.py
security_scripts/information/lib/measurements.py
security_scripts/information/lib/repos.py
security_scripts/information/lib/s3.py
security_scripts/information/lib/secrets.py
security_scripts/information/lib/shlog.py
security_scripts/information/lib/tag_counter.py
security_scripts/information/lib/tags.py
security_scripts/information/lib/test.py
security_scripts/information/lib/untagged_lister.py
security_scripts/information/lib/vanilla_utils.py
security_scripts/information/lib/xs3.py
security_scripts/information/lib/xtags.py
scimma_security_scripts-2.4b1.dist-info/LICENSE
scimma_security_scripts-2.4b1.dist-info/METADATA
scimma_security_scripts-2.4b1.dist-info/WHEEL
scimma_security_scripts-2.4b1.dist-info/entry_points.txt
scimma_security_scripts-2.4b1.dist-info/top_level.txt
scimma_security_scripts-2.4b1.dist-info/RECORD
