Metadata-Version: 2.1
Name: scimma-security-scripts
Version: 2.4b1
Summary: SCiMMA security scripts
Home-page: https://github.com/scimma/security-scripts
Author: Vladislav Ekimtcov, Donald Petravick
Author-email: ekimtco2@illinois.edu
License: UNKNOWN
Platform: UNKNOWN
Classifier: Programming Language :: Python :: 3
Classifier: License :: OSI Approved :: MIT License
Classifier: Operating System :: OS Independent
Requires-Python: >=3.6
Requires-Dist: boto3
Requires-Dist: tabulate
Requires-Dist: regex
Requires-Dist: pandas
Requires-Dist: openpyxl
Requires-Dist: networkx-query
Requires-Dist: pydot
Requires-Dist: pygraphviz
Requires-Dist: netaddr
